[
{"area_group":"AREA 1","area_name":"AL MUTAWAH","mosquito_risk":"Low","fly_risk":"Moderate","ulv_status":"Suitable","risk_score":25,"risk_level":"Low","map_color":"Green","need_attention":false,"ulv_suspend":false,"recommendation":"Maintain routine ULV; monitor fly activity"},
{"area_group":"AREA 1","area_name":"AL MUTARID","mosquito_risk":"Low","fly_risk":"Moderate","ulv_status":"Suitable","risk_score":25,"risk_level":"Low","map_color":"Green","need_attention":false,"ulv_suspend":false,"recommendation":"Maintain routine ULV; monitor fly activity"},
{"area_group":"AREA 1","area_name":"AL JAHILI","mosquito_risk":"Low","fly_risk":"Moderate","ulv_status":"Suitable","risk_score":25,"risk_level":"Low","map_color":"Green","need_attention":false,"ulv_suspend":false,"recommendation":"Maintain routine ULV; monitor fly activity"},
{"area_group":"AREA 1","area_name":"CENTRAL DISTRICT","mosquito_risk":"Low","fly_risk":"Moderate","ulv_status":"Suitable","risk_score":25,"risk_level":"Low","map_color":"Green","need_attention":false,"ulv_suspend":false,"recommendation":"Maintain routine ULV; monitor fly activity"},
{"area_group":"AREA 2","area_name":"MAZYAD","mosquito_risk":"Low","fly_risk":"Moderate","ulv_status":"Suitable","risk_score":25,"risk_level":"Low","map_color":"Green","need_attention":false,"ulv_suspend":false,"recommendation":"Routine monitoring; focus on fly control"},
{"area_group":"AREA 2","area_name":"AL NOUD","mosquito_risk":"Low","fly_risk":"Moderate","ulv_status":"Suitable","risk_score":25,"risk_level":"Low","map_color":"Green","need_attention":false,"ulv_suspend":false,"recommendation":"Routine monitoring; focus on fly control"},
{"area_group":"AREA 2","area_name":"UM GHAFAH","mosquito_risk":"Low","fly_risk":"Moderate","ulv_status":"Suitable","risk_score":25,"risk_level":"Low","map_color":"Green","need_attention":false,"ulv_suspend":false,"recommendation":"Routine monitoring; focus on fly control"},
{"area_group":"AREA 2","area_name":"SA'","mosquito_risk":"Low","fly_risk":"Moderate","ulv_status":"Suitable","risk_score":25,"risk_level":"Low","map_color":"Green","need_attention":false,"ulv_suspend":false,"recommendation":"Routine monitoring; focus on fly control"},
{"area_group":"AREA 2","area_name":"MALAQIT","mosquito_risk":"Low","fly_risk":"Moderate","ulv_status":"Suitable","risk_score":25,"risk_level":"Low","map_color":"Green","need_attention":false,"ulv_suspend":false,"recommendation":"Routine monitoring; focus on fly control"},
{"area_group":"AREA 2","area_name":"AL AFLAJ","mosquito_risk":"Low","fly_risk":"Moderate","ulv_status":"Suitable","risk_score":25,"risk_level":"Low","map_color":"Green","need_attention":false,"ulv_suspend":false,"recommendation":"Routine monitoring; focus on fly control"},
{"area_group":"AREA 2","area_name":"KHATM AL SHIKLAH","mosquito_risk":"Low","fly_risk":"Moderate","ulv_status":"Suitable","risk_score":25,"risk_level":"Low","map_color":"Green","need_attention":false,"ulv_suspend":false,"recommendation":"Routine monitoring; focus on fly control"},
{"area_group":"AREA 2","area_name":"AL RUWAYDAT","mosquito_risk":"Low","fly_risk":"Moderate","ulv_status":"Suitable","risk_score":25,"risk_level":"Low","map_color":"Green","need_attention":false,"ulv_suspend":false,"recommendation":"Routine monitoring; focus on fly control"},
{"area_group":"AREA 2","area_name":"AL SHUWAIMAH","mosquito_risk":"Low","fly_risk":"Moderate","ulv_status":"Suitable","risk_score":25,"risk_level":"Low","map_color":"Green","need_attention":false,"ulv_suspend":false,"recommendation":"Routine monitoring; focus on fly control"},
{"area_group":"AREA 2","area_name":"AL SAROUJ","mosquito_risk":"Low","fly_risk":"Moderate","ulv_status":"Suitable","risk_score":25,"risk_level":"Low","map_color":"Green","need_attention":false,"ulv_suspend":false,"recommendation":"Routine monitoring; focus on fly control"},
{"area_group":"AREA 2","area_name":"AL DHAHIR","mosquito_risk":"Low","fly_risk":"Moderate","ulv_status":"Suitable","risk_score":25,"risk_level":"Low","map_color":"Green","need_attention":false,"ulv_suspend":false,"recommendation":"Routine monitoring; focus on fly control"},
{"area_group":"AREA 3","area_name":"INDUSTRIAL AREA","mosquito_risk":"Low","fly_risk":"Moderate","ulv_status":"Caution","risk_score":35,"risk_level":"Low","map_color":"Green","need_attention":false,"ulv_suspend":false,"recommendation":"ULV caution due to wind; enhance fly sanitation"},
{"area_group":"AREA 3","area_name":"NI'MAH","mosquito_risk":"Low","fly_risk":"Moderate","ulv_status":"Caution","risk_score":35,"risk_level":"Low","map_color":"Green","need_attention":false,"ulv_suspend":false,"recommendation":"ULV caution due to wind; enhance fly sanitation"},
{"area_group":"AREA 3","area_name":"JABAL HAFEET","mosquito_risk":"Low","fly_risk":"Moderate","ulv_status":"Caution","risk_score":35,"risk_level":"Low","map_color":"Green","need_attention":false,"ulv_suspend":false,"recommendation":"ULV caution due to wind; enhance fly sanitation"},
{"area_group":"AREA 3","area_name":"MBAZZARAH AL KHADRA","mosquito_risk":"Low","fly_risk":"Moderate","ulv_status":"Caution","risk_score":35,"risk_level":"Low","map_color":"Green","need_attention":false,"ulv_suspend":false,"recommendation":"ULV caution due to wind; enhance fly sanitation"},
{"area_group":"AREA 3","area_name":"SHIAB AL ASHKHAR","mosquito_risk":"Low","fly_risk":"Moderate","ulv_status":"Caution","risk_score":35,"risk_level":"Low","map_color":"Green","need_attention":false,"ulv_suspend":false,"recommendation":"ULV caution due to wind; enhance fly sanitation"},
{"area_group":"AREA 3","area_name":"SHI'BAT AL WUTAH","mosquito_risk":"Low","fly_risk":"Moderate","ulv_status":"Caution","risk_score":35,"risk_level":"Low","map_color":"Green","need_attention":false,"ulv_suspend":false,"recommendation":"ULV caution due to wind; enhance fly sanitation"},
{"area_group":"AREA 3","area_name":"AIN AL FAYDAH","mosquito_risk":"Low","fly_risk":"Moderate","ulv_status":"Caution","risk_score":35,"risk_level":"Low","map_color":"Green","need_attention":false,"ulv_suspend":false,"recommendation":"ULV caution due to wind; enhance fly sanitation"},
{"area_group":"AREA 3","area_name":"AL DHAHRAH","mosquito_risk":"Low","fly_risk":"Moderate","ulv_status":"Caution","risk_score":35,"risk_level":"Low","map_color":"Green","need_attention":false,"ulv_suspend":false,"recommendation":"ULV caution due to wind; enhance fly sanitation"},
{"area_group":"AREA 4","area_name":"FALAJ HAZZA'","mosquito_risk":"Low","fly_risk":"Elevated","ulv_status":"Suspend","risk_score":70,"risk_level":"Elevated","map_color":"Orange","need_attention":true,"ulv_suspend":true,"recommendation":"Suspend ULV on windy days; enhance fly control"},
{"area_group":"AREA 4